gsoft_py_utils/auto_notify.py
gsoft_py_utils/esclient.py
gsoft_py_utils/esdupefilter.py
gsoft_py_utils/eswriter.py
gsoft_py_utils/file/fileutils.py
gsoft_py_utils/login/baseclient.py
gsoft_py_utils/login/douban_client.py
gsoft_py_utils/login/douban_login.py
gsoft_py_utils/onebot_client.py
gsoft_py_utils-0.0.4.dist-info/METADATA
gsoft_py_utils-0.0.4.dist-info/WHEEL
gsoft_py_utils-0.0.4.dist-info/RECORD
